{
  "schema_version": "deck_recipe_runtime_fixture_v1",
  "fixture_id": "runtime_fixture_m44_recipe_001_link_joker_legion_bermuda_triangle_m45_04",
  "fixture_scope": "offline_runtime_test_fixture",
  "recipe_id": "m44_recipe_001",
  "source_artifact": "outputs/target_slice/m45_02_third_slice_human_accepted_repair_artifact.json",
  "selected_target": {
    "slice": "Third Offline Slice",
    "era_preset": "link_joker_legion_mate",
    "group": "เบอร์มิวด้า ไทรแองเกิล",
    "group_field": "clan",
    "rank": 1,
    "priority_score": 95.0,
    "best_era_candidates": 2179,
    "mechanic_tier": 2,
    "mechanic_tier_label": "OG Keywords",
    "priority_reasons": [
      "HIGH_PRIORITY",
      "simple_mechanics",
      "rich_combo_pool",
      "large_card_pool"
    ]
  },
  "format_policy": {
    "slice": "Third Offline Slice",
    "era_preset": "link_joker_legion_mate",
    "group": "เบอร์มิวด้า ไทรแองเกิล",
    "group_field": "clan"
  },
  "main_deck": [
    {
      "card_id": "EB06-003TH",
      "quantity": 4
    },
    {
      "card_id": "EB06-009TH",
      "quantity": 4
    },
    {
      "card_id": "EB06-011TH",
      "quantity": 4
    },
    {
      "card_id": "EB06-013TH",
      "quantity": 2
    },
    {
      "card_id": "EB06-021TH",
      "quantity": 1
    },
    {
      "card_id": "EB06-022TH",
      "quantity": 3
    },
    {
      "card_id": "EB06-023TH",
      "quantity": 4
    },
    {
      "card_id": "EB06-026TH",
      "quantity": 1
    },
    {
      "card_id": "EB06-029TH",
      "quantity": 4
    },
    {
      "card_id": "EB06-031TH",
      "quantity": 4
    },
    {
      "card_id": "EB06-032TH",
      "quantity": 4
    },
    {
      "card_id": "EB06-033TH",
      "quantity": 4
    },
    {
      "card_id": "EB06-S01TH",
      "quantity": 4
    },
    {
      "card_id": "EB06-S05TH",
      "quantity": 3
    },
    {
      "card_id": "EB10-007TH-B",
      "quantity": 4
    }
  ],
  "count_summary": {
    "main_deck_count": 50,
    "trigger_count": 16,
    "trigger_counts": {
      "Critical": 4,
      "Draw": 4,
      "Heal": 4,
      "Stand": 4
    },
    "grade_counts": {
      "0": 17,
      "1": 14,
      "2": 11,
      "3": 8
    },
    "clan_counts": {
      "เบอร์มิวด้า ไทรแองเกิล": 50
    }
  },
  "source_packages": {
    "manual_repair_package_id": "m44_recipe_001_manual_overlap_pkg_001",
    "source_grade_profile_package_id": "m44_recipe_001_grade_profile_pkg_001",
    "combined_repair_package_id": "m44_recipe_001_combined_manual_grade_pkg_001"
  },
  "runtime_boundaries": {
    "test_fixture_only": true,
    "auto_injected_into_player_decks": false,
    "bot_playbook_enabled": false,
    "ui_deck_library_mutated": false,
    "game_state_mutated": false
  }
}
